[
null,
{"id":1,"animationId":6,"description":"[Меч] Легкий и удобный в ношении меч с коротким\nлезвием.","etypeId":1,"traits":[{"code":31,"dataId":1,"value":0},{"code":22,"dataId":0,"value":0}],"iconIndex":97,"name":"Короткий меч[Ур.1]","note":"<weight:4>\n<require level 1>","params":[0,0,8,0,0,0,0,0],"price":300,"wtypeId":2},
{"id":2,"animationId":6,"description":"[Меч] Длинный боевой меч с остро заточенным лезвием.","etypeId":1,"traits":[{"code":31,"dataId":1,"value":0},{"code":22,"dataId":0,"value":0},{"code":55,"dataId":1,"value":1}],"iconIndex":97,"name":"Длинный меч[Ур.2]","note":"<weight:7>\n<require level 2>","params":[0,0,12,0,0,0,0,0],"price":670,"wtypeId":2},
{"id":3,"animationId":6,"description":"[Меч] Широкий меч с изогнутым клинком.","etypeId":1,"traits":[{"code":31,"dataId":1,"value":0},{"code":22,"dataId":0,"value":0}],"iconIndex":123,"name":"Фальшион[Ур.3]","note":"<weight:3>\n<require level 3>","params":[0,0,18,0,0,0,0,0],"price":1480,"wtypeId":2},
{"id":4,"animationId":6,"description":"[Меч] Длинный меч, выкованный из мифрила.","etypeId":1,"traits":[{"code":31,"dataId":1,"value":0},{"code":22,"dataId":0,"value":0}],"iconIndex":1305,"name":"Мифриловый меч[Ур.5]","note":"<weight:3>\n<require level 4>","params":[0,0,25,0,0,0,0,0],"price":3890,"wtypeId":2},
{"id":5,"animationId":6,"description":"[Меч] Меч, выкованный из клыков дракона.","etypeId":1,"traits":[{"code":31,"dataId":1,"value":0},{"code":22,"dataId":0,"value":0}],"iconIndex":1265,"name":"Драконий клинок[Ур.10]","note":"<weight:3>\n<require level 10>","params":[0,0,36,0,0,0,0,0],"price":6970,"wtypeId":2},
{"id":6,"animationId":24,"description":"[Меч] Невероятный мечь позволяющий своему владельцу\nнаносить непрерывно две атаки.","etypeId":1,"traits":[{"code":31,"dataId":4,"value":0},{"code":34,"dataId":0,"value":1},{"code":14,"dataId":10,"value":1}],"iconIndex":1321,"name":"Резак[Ур.15]","note":"<weight:3>\n<itemRare:2>\n<require level 15>","params":[0,0,44,5,0,0,0,0],"price":9320,"wtypeId":2},
{"id":7,"animationId":11,"description":"[Посох] Популярный недорогой посох.","etypeId":1,"traits":[{"code":31,"dataId":1,"value":0},{"code":22,"dataId":0,"value":0}],"iconIndex":101,"name":"Деревянный посох[Ур.1]","note":"<weight:1>\n<require level 1>","params":[0,0,2,0,8,3,0,0],"price":280,"wtypeId":6},
{"id":8,"animationId":1,"description":"[Посох] Жезл, немного увеличивающий магические\nспособности владельца.","etypeId":1,"traits":[{"code":31,"dataId":1,"value":0},{"code":22,"dataId":0,"value":0}],"iconIndex":1270,"name":"Магический жезл[Ур.2]","note":"<weight:2>\n<require level 2>","params":[0,0,3,0,12,6,0,0],"price":780,"wtypeId":6},
{"id":9,"animationId":1,"description":"[Посох] Серебряный жезл, увеличивающий магические\nспособности владельца.","etypeId":1,"traits":[{"code":31,"dataId":1,"value":0},{"code":22,"dataId":0,"value":0}],"iconIndex":1271,"name":"Жезл силы[Ур.3]","note":"<weight:2>\n<require level 3>","params":[0,0,5,0,21,12,0,0],"price":1680,"wtypeId":6},
{"id":10,"animationId":1,"description":"[Посох] Мифриловый жезл, увеличивающий магические\nспособности владельца.","etypeId":1,"traits":[{"code":31,"dataId":1,"value":0},{"code":22,"dataId":0,"value":0}],"iconIndex":1315,"name":"Мифриловый жезл[Ур.6]","note":"<weight:2>\n<require level 6>","params":[0,0,12,0,32,24,0,0],"price":4120,"wtypeId":6},
{"id":11,"animationId":1,"description":"[Посох] Драконий посох, увеличивающий магические\nспособности владельца.","etypeId":1,"traits":[{"code":31,"dataId":1,"value":0},{"code":22,"dataId":0,"value":0}],"iconIndex":1405,"name":"Драконий посох[Ур.12]","note":"<weight:2>\n<require level 12>","params":[0,0,18,0,45,32,0,0],"price":7680,"wtypeId":6},
{"id":12,"animationId":13,"description":"[Посох] Посох обладающий огненой стихией и увеличивающий\nМаг. атаку на 10%","etypeId":1,"traits":[{"code":31,"dataId":2,"value":0},{"code":22,"dataId":0,"value":0},{"code":21,"dataId":4,"value":1.1}],"iconIndex":1399,"name":"Жезл Огня[Ур.15]","note":"<weight:2>\n<itemRare:2>\n<require level 15>","params":[0,0,22,0,52,46,0,0],"price":9200,"wtypeId":6},
{"id":13,"animationId":5,"description":"[Посох]Старый посох Эрика, он не плохо сохранился и думаю\nон сможет пригодится. Свойство: две атаки подряд.","etypeId":1,"traits":[{"code":31,"dataId":4,"value":0},{"code":22,"dataId":0,"value":0},{"code":34,"dataId":0,"value":1}],"iconIndex":1404,"name":"Посох Эрика[Ур.13]","note":"<weight:2>\n<itemRare:2>\n<require level 13>","params":[0,0,18,0,30,30,0,0],"price":8100,"wtypeId":6},
{"id":14,"animationId":0,"description":"","etypeId":1,"traits":[{"code":31,"dataId":1,"value":0},{"code":22,"dataId":0,"value":0}],"iconIndex":0,"name":"","note":"","params":[0,0,0,0,0,0,0,0],"price":0,"wtypeId":0},
{"id":15,"animationId":0,"description":"","etypeId":1,"traits":[{"code":31,"dataId":1,"value":0},{"code":22,"dataId":0,"value":0}],"iconIndex":0,"name":"","note":"","params":[0,0,0,0,0,0,0,0],"price":0,"wtypeId":0},
{"id":16,"animationId":0,"description":"","etypeId":1,"traits":[{"code":31,"dataId":1,"value":0},{"code":22,"dataId":0,"value":0}],"iconIndex":0,"name":"","note":"","params":[0,0,0,0,0,0,0,0],"price":0,"wtypeId":0},
{"id":17,"animationId":0,"description":"","etypeId":1,"traits":[{"code":31,"dataId":1,"value":0},{"code":22,"dataId":0,"value":0}],"iconIndex":0,"name":"","note":"","params":[0,0,0,0,0,0,0,0],"price":0,"wtypeId":0},
{"id":18,"animationId":0,"description":"","etypeId":1,"traits":[{"code":31,"dataId":1,"value":0},{"code":22,"dataId":0,"value":0}],"iconIndex":0,"name":"","note":"","params":[0,0,0,0,0,0,0,0],"price":0,"wtypeId":0},
{"id":19,"animationId":0,"description":"","etypeId":1,"traits":[{"code":31,"dataId":1,"value":0},{"code":22,"dataId":0,"value":0}],"iconIndex":0,"name":"","note":"","params":[0,0,0,0,0,0,0,0],"price":0,"wtypeId":0},
{"id":20,"animationId":0,"description":"","etypeId":1,"traits":[{"code":31,"dataId":1,"value":0},{"code":22,"dataId":0,"value":0}],"iconIndex":0,"name":"","note":"","params":[0,0,0,0,0,0,0,0],"price":0,"wtypeId":0},
{"id":21,"animationId":0,"description":"","etypeId":1,"traits":[{"code":31,"dataId":1,"value":0},{"code":22,"dataId":0,"value":0}],"iconIndex":0,"name":"","note":"","params":[0,0,0,0,0,0,0,0],"price":0,"wtypeId":0},
{"id":22,"animationId":0,"description":"","etypeId":1,"traits":[{"code":31,"dataId":1,"value":0},{"code":22,"dataId":0,"value":0}],"iconIndex":0,"name":"","note":"","params":[0,0,0,0,0,0,0,0],"price":0,"wtypeId":0},
{"id":23,"animationId":0,"description":"","etypeId":1,"traits":[{"code":31,"dataId":1,"value":0},{"code":22,"dataId":0,"value":0}],"iconIndex":0,"name":"","note":"","params":[0,0,0,0,0,0,0,0],"price":0,"wtypeId":0},
{"id":24,"animationId":0,"description":"","etypeId":1,"traits":[{"code":31,"dataId":1,"value":0},{"code":22,"dataId":0,"value":0}],"iconIndex":0,"name":"","note":"","params":[0,0,0,0,0,0,0,0],"price":0,"wtypeId":0},
{"id":25,"animationId":0,"description":"","etypeId":1,"traits":[{"code":31,"dataId":1,"value":0},{"code":22,"dataId":0,"value":0}],"iconIndex":0,"name":"","note":"","params":[0,0,0,0,0,0,0,0],"price":0,"wtypeId":0},
{"id":26,"animationId":0,"description":"","etypeId":1,"traits":[{"code":31,"dataId":1,"value":0},{"code":22,"dataId":0,"value":0}],"iconIndex":0,"name":"","note":"","params":[0,0,0,0,0,0,0,0],"price":0,"wtypeId":0},
{"id":27,"animationId":0,"description":"","etypeId":1,"traits":[{"code":31,"dataId":1,"value":0},{"code":22,"dataId":0,"value":0}],"iconIndex":0,"name":"","note":"","params":[0,0,0,0,0,0,0,0],"price":0,"wtypeId":0},
{"id":28,"animationId":0,"description":"","etypeId":1,"traits":[{"code":31,"dataId":1,"value":0},{"code":22,"dataId":0,"value":0}],"iconIndex":0,"name":"","note":"","params":[0,0,0,0,0,0,0,0],"price":0,"wtypeId":0},
{"id":29,"animationId":0,"description":"","etypeId":1,"traits":[{"code":31,"dataId":1,"value":0},{"code":22,"dataId":0,"value":0}],"iconIndex":0,"name":"","note":"","params":[0,0,0,0,0,0,0,0],"price":0,"wtypeId":0},
{"id":30,"animationId":0,"description":"","etypeId":1,"traits":[{"code":31,"dataId":1,"value":0},{"code":22,"dataId":0,"value":0}],"iconIndex":0,"name":"","note":"","params":[0,0,0,0,0,0,0,0],"price":0,"wtypeId":0},
{"id":31,"animationId":1,"description":"[Перчатка] Боевая перчатка с шипами на костяшках\nпальцев.","etypeId":1,"traits":[{"code":31,"dataId":1,"value":0},{"code":22,"dataId":0,"value":0},{"code":54,"dataId":2,"value":1},{"code":34,"dataId":0,"value":1}],"iconIndex":106,"name":"Цестус[Ур.2]","note":"<weight:4>\n<require level 2>","params":[0,0,5,5,0,0,0,0],"price":360,"wtypeId":11},
{"id":32,"animationId":16,"description":"[Коготь] Кистевое оружие с четырьмя короткими когтями.","etypeId":1,"traits":[{"code":31,"dataId":1,"value":0},{"code":22,"dataId":0,"value":0},{"code":54,"dataId":2,"value":1},{"code":34,"dataId":0,"value":1}],"iconIndex":1203,"name":"Коготь тигра[Ур.4]","note":"<weight:2>\n<require level 4>","params":[0,0,12,8,0,0,0,0],"price":980,"wtypeId":10},
{"id":33,"animationId":16,"description":"[Коготь] Кистевое оружие с железными когтями.","etypeId":1,"traits":[{"code":31,"dataId":1,"value":0},{"code":22,"dataId":0,"value":0},{"code":54,"dataId":2,"value":1},{"code":34,"dataId":0,"value":1}],"iconIndex":1357,"name":"Железный коготь[Ур.6]","note":"<weight:2>\n<require level 6>","params":[0,0,20,15,0,0,0,0],"price":1560,"wtypeId":10},
{"id":34,"animationId":16,"description":"[Коготь] Кистевое оружие с мифриловыми когтями.","etypeId":1,"traits":[{"code":31,"dataId":1,"value":0},{"code":22,"dataId":0,"value":0},{"code":54,"dataId":2,"value":1},{"code":34,"dataId":0,"value":1}],"iconIndex":1354,"name":"Мифриловый коготь[Ур.9]","note":"<weight:2>\n<require level 9>","params":[0,0,25,18,0,0,0,0],"price":3480,"wtypeId":10},
{"id":35,"animationId":16,"description":"[Коготь] Кистевое оружие с драконьими когтями.","etypeId":1,"traits":[{"code":31,"dataId":1,"value":0},{"code":22,"dataId":0,"value":0},{"code":54,"dataId":2,"value":1},{"code":34,"dataId":0,"value":1}],"iconIndex":1362,"name":"Драконий коготь[Ур.12]","note":"<weight:2>\n<itemRare:2>","params":[0,0,32,21,0,0,0,0],"price":6890,"wtypeId":10},
{"id":36,"animationId":16,"description":"[Коготь] Кистевое оружие с драконьими когтями.","etypeId":1,"traits":[{"code":31,"dataId":1,"value":0},{"code":22,"dataId":0,"value":0},{"code":54,"dataId":2,"value":1},{"code":34,"dataId":0,"value":1}],"iconIndex":1362,"name":"Драконий коготь","note":"<weight:2>\n<itemRare:2>","params":[0,0,32,21,0,0,0,0],"price":6890,"wtypeId":10},
{"id":37,"animationId":0,"description":"","etypeId":1,"traits":[{"code":31,"dataId":1,"value":0},{"code":22,"dataId":0,"value":0}],"iconIndex":0,"name":"","note":"","params":[0,0,0,0,0,0,0,0],"price":0,"wtypeId":0},
{"id":38,"animationId":0,"description":"","etypeId":1,"traits":[{"code":31,"dataId":1,"value":0},{"code":22,"dataId":0,"value":0}],"iconIndex":0,"name":"","note":"","params":[0,0,0,0,0,0,0,0],"price":0,"wtypeId":0},
{"id":39,"animationId":0,"description":"","etypeId":1,"traits":[{"code":31,"dataId":1,"value":0},{"code":22,"dataId":0,"value":0}],"iconIndex":0,"name":"","note":"","params":[0,0,0,0,0,0,0,0],"price":0,"wtypeId":0},
{"id":40,"animationId":0,"description":"","etypeId":1,"traits":[{"code":31,"dataId":1,"value":0},{"code":22,"dataId":0,"value":0}],"iconIndex":0,"name":"","note":"","params":[0,0,0,0,0,0,0,0],"price":0,"wtypeId":0},
{"id":41,"animationId":0,"description":"","etypeId":1,"traits":[{"code":31,"dataId":1,"value":0},{"code":22,"dataId":0,"value":0}],"iconIndex":0,"name":"","note":"","params":[0,0,0,0,0,0,0,0],"price":0,"wtypeId":0},
{"id":42,"animationId":0,"description":"","etypeId":1,"traits":[{"code":31,"dataId":1,"value":0},{"code":22,"dataId":0,"value":0}],"iconIndex":0,"name":"","note":"","params":[0,0,0,0,0,0,0,0],"price":0,"wtypeId":0},
{"id":43,"animationId":0,"description":"","etypeId":1,"traits":[{"code":31,"dataId":1,"value":0},{"code":22,"dataId":0,"value":0}],"iconIndex":0,"name":"","note":"","params":[0,0,0,0,0,0,0,0],"price":0,"wtypeId":0},
{"id":44,"animationId":6,"description":"[Кинжал] Короткий боевой клинок.","etypeId":1,"traits":[{"code":31,"dataId":1,"value":0},{"code":22,"dataId":0,"value":0}],"iconIndex":1345,"name":"Кинжал[Ур.2]","note":"<weight:1>\n<require level 2>","params":[0,0,9,0,0,0,0,0],"price":690,"wtypeId":1},
{"id":45,"animationId":6,"description":"[Кинжал] Кинжал с толстым и прочным лезвием.","etypeId":1,"traits":[{"code":31,"dataId":1,"value":0},{"code":22,"dataId":0,"value":0}],"iconIndex":1346,"name":"Мачете[Ур.4]","note":"<weight:1>\n<require level 4>","params":[0,0,12,0,0,0,0,0],"price":1280,"wtypeId":1},
{"id":46,"animationId":6,"description":"[Кинжал] Кинжал, выкованный из мифрила.","etypeId":1,"traits":[{"code":31,"dataId":1,"value":0},{"code":22,"dataId":0,"value":0}],"iconIndex":1350,"name":"Мифриловый кинжал[Ур.8]","note":"<weight:1>\n<require level 8>","params":[0,0,18,0,0,0,0,0],"price":2930,"wtypeId":1},
{"id":47,"animationId":6,"description":"[Кинжал] Кинжал, выкованный из драконьих клыков.","etypeId":1,"traits":[{"code":31,"dataId":1,"value":0},{"code":22,"dataId":0,"value":0}],"iconIndex":1347,"name":"Драконий кинжал[Ур.12]","note":"<require level 12>","params":[0,0,23,0,0,0,0,0],"price":5820,"wtypeId":1},
{"id":48,"animationId":0,"description":"","etypeId":1,"traits":[{"code":31,"dataId":1,"value":0},{"code":22,"dataId":0,"value":0}],"iconIndex":0,"name":"","note":"","params":[0,0,0,0,0,0,0,0],"price":0,"wtypeId":0},
{"id":49,"animationId":0,"description":"","etypeId":1,"traits":[{"code":31,"dataId":1,"value":0},{"code":22,"dataId":0,"value":0}],"iconIndex":0,"name":"","note":"","params":[0,0,0,0,0,0,0,0],"price":0,"wtypeId":0},
{"id":50,"animationId":0,"description":"","etypeId":1,"traits":[{"code":31,"dataId":1,"value":0},{"code":22,"dataId":0,"value":0}],"iconIndex":0,"name":"","note":"","params":[0,0,0,0,0,0,0,0],"price":0,"wtypeId":0},
{"id":51,"animationId":0,"description":"","etypeId":1,"traits":[{"code":31,"dataId":1,"value":0},{"code":22,"dataId":0,"value":0}],"iconIndex":0,"name":"","note":"","params":[0,0,0,0,0,0,0,0],"price":0,"wtypeId":0},
{"id":52,"animationId":0,"description":"","etypeId":1,"traits":[{"code":31,"dataId":1,"value":0},{"code":22,"dataId":0,"value":0}],"iconIndex":0,"name":"","note":"","params":[0,0,0,0,0,0,0,0],"price":0,"wtypeId":0},
{"id":53,"animationId":0,"description":"","etypeId":1,"traits":[{"code":31,"dataId":1,"value":0},{"code":22,"dataId":0,"value":0}],"iconIndex":0,"name":"","note":"","params":[0,0,0,0,0,0,0,0],"price":0,"wtypeId":0},
{"id":54,"animationId":7,"description":"[Меч] Меч, пренадлежавший великому полководцу.\nГлавной особенностью является двойной удар.","etypeId":1,"traits":[{"code":31,"dataId":1,"value":0},{"code":22,"dataId":0,"value":0.05},{"code":34,"dataId":0,"value":2}],"iconIndex":1331,"name":"Меч Генерала","note":"<weight:5>\n<itemRare:2>","params":[0,0,30,5,0,0,0,0],"price":7920,"wtypeId":2},
{"id":55,"animationId":8,"description":"[Меч] Ходит легенда, что этот меч выкован самим Арчибальдом,\nстарейшим драконом. Скорее всего это не правда.","etypeId":1,"traits":[{"code":31,"dataId":2,"value":0},{"code":22,"dataId":6,"value":0.5},{"code":14,"dataId":4,"value":1}],"iconIndex":1905,"name":"Драконий Меч","note":"<weight:4>\n<itemRare:3>","params":[0,0,42,5,0,0,0,0],"price":8000,"wtypeId":2},
{"id":56,"animationId":10,"description":"[Меч] Чудесный меч, наделённый магией грома.\nУвеличение шанса на критический удар.","etypeId":1,"traits":[{"code":31,"dataId":4,"value":0},{"code":22,"dataId":2,"value":0.5},{"code":14,"dataId":10,"value":1}],"iconIndex":1904,"name":"Меч Грома","note":"<weight:4>\n<itemRare:3>","params":[0,0,44,5,0,0,0,0],"price":8500,"wtypeId":2},
{"id":57,"animationId":0,"description":"","etypeId":1,"traits":[{"code":31,"dataId":1,"value":0},{"code":22,"dataId":0,"value":0}],"iconIndex":0,"name":"","note":"","params":[0,0,0,0,0,0,0,0],"price":0,"wtypeId":0},
{"id":58,"animationId":0,"description":"","etypeId":1,"traits":[{"code":31,"dataId":1,"value":0},{"code":22,"dataId":0,"value":0}],"iconIndex":0,"name":"","note":"","params":[0,0,0,0,0,0,0,0],"price":0,"wtypeId":0},
{"id":59,"animationId":0,"description":"","etypeId":1,"traits":[{"code":31,"dataId":1,"value":0},{"code":22,"dataId":0,"value":0}],"iconIndex":0,"name":"","note":"","params":[0,0,0,0,0,0,0,0],"price":0,"wtypeId":0},
{"id":60,"animationId":0,"description":"","etypeId":1,"traits":[{"code":31,"dataId":1,"value":0},{"code":22,"dataId":0,"value":0}],"iconIndex":0,"name":"","note":"","params":[0,0,0,0,0,0,0,0],"price":0,"wtypeId":0},
{"id":61,"animationId":0,"description":"","etypeId":1,"traits":[{"code":31,"dataId":1,"value":0},{"code":22,"dataId":0,"value":0}],"iconIndex":0,"name":"","note":"","params":[0,0,0,0,0,0,0,0],"price":0,"wtypeId":0},
{"id":62,"animationId":0,"description":"","etypeId":1,"traits":[{"code":31,"dataId":1,"value":0},{"code":22,"dataId":0,"value":0}],"iconIndex":0,"name":"","note":"","params":[0,0,0,0,0,0,0,0],"price":0,"wtypeId":0},
{"id":63,"animationId":0,"description":"","etypeId":1,"traits":[{"code":31,"dataId":1,"value":0},{"code":22,"dataId":0,"value":0}],"iconIndex":0,"name":"","note":"","params":[0,0,0,0,0,0,0,0],"price":0,"wtypeId":0},
{"id":64,"animationId":0,"description":"","etypeId":1,"traits":[{"code":31,"dataId":1,"value":0},{"code":22,"dataId":0,"value":0}],"iconIndex":0,"name":"","note":"","params":[0,0,0,0,0,0,0,0],"price":0,"wtypeId":0},
{"id":65,"animationId":0,"description":"","etypeId":1,"traits":[{"code":31,"dataId":1,"value":0},{"code":22,"dataId":0,"value":0}],"iconIndex":0,"name":"","note":"","params":[0,0,0,0,0,0,0,0],"price":0,"wtypeId":0},
{"id":66,"animationId":12,"description":"","etypeId":1,"traits":[{"code":31,"dataId":9,"value":0},{"code":22,"dataId":8,"value":0.1},{"code":12,"dataId":5,"value":0.2},{"code":12,"dataId":3,"value":0.2},{"code":13,"dataId":8,"value":0.1},{"code":21,"dataId":4,"value":1.15},{"code":51,"dataId":6,"value":1}],"iconIndex":112,"name":"Посох Нежити","note":"","params":[0,100,0,0,35,0,0,10],"price":500,"wtypeId":6},
{"id":67,"animationId":11,"description":"","etypeId":1,"traits":[{"code":31,"dataId":1,"value":0},{"code":22,"dataId":2,"value":0.17},{"code":11,"dataId":1,"value":0.3},{"code":12,"dataId":0,"value":0.1},{"code":13,"dataId":1,"value":0.15},{"code":34,"dataId":0,"value":1},{"code":51,"dataId":7,"value":1},{"code":32,"dataId":1,"value":0.15}],"iconIndex":4383,"name":"Быстрее Ветра","note":"","params":[0,0,45,0,0,0,15,0],"price":500,"wtypeId":7},
{"id":68,"animationId":13,"description":"","etypeId":1,"traits":[{"code":31,"dataId":1,"value":0},{"code":22,"dataId":0,"value":0.1},{"code":51,"dataId":2,"value":1},{"code":22,"dataId":2,"value":0.1}],"iconIndex":4785,"name":"Меч Грома","note":"10-20","params":[50,0,45,0,0,0,10,0],"price":100,"wtypeId":2},
{"id":69,"animationId":13,"description":"","etypeId":1,"traits":[{"code":31,"dataId":1,"value":0},{"code":22,"dataId":0,"value":0.14},{"code":22,"dataId":2,"value":0.14},{"code":51,"dataId":2,"value":1}],"iconIndex":4747,"name":"Лазурный Меч","note":"20-30","params":[90,0,60,0,0,0,13,0],"price":0,"wtypeId":2},
{"id":70,"animationId":13,"description":"","etypeId":1,"traits":[{"code":31,"dataId":1,"value":0},{"code":22,"dataId":0,"value":0.18},{"code":51,"dataId":2,"value":1},{"code":22,"dataId":2,"value":0.18},{"code":12,"dataId":0,"value":1.1}],"iconIndex":4132,"name":"Кровавый Меч","note":"30-40","params":[135,0,75,0,0,0,18,0],"price":0,"wtypeId":2},
{"id":71,"animationId":13,"description":"","etypeId":1,"traits":[{"code":31,"dataId":1,"value":0},{"code":22,"dataId":0,"value":0.27},{"code":22,"dataId":2,"value":0.25},{"code":51,"dataId":2,"value":1},{"code":12,"dataId":3,"value":1.15},{"code":13,"dataId":1,"value":1.15}],"iconIndex":799,"name":"Демонический Меч","note":"40-50","params":[180,0,100,0,0,0,25,0],"price":0,"wtypeId":2},
{"id":72,"animationId":13,"description":"","etypeId":1,"traits":[{"code":31,"dataId":1,"value":0},{"code":22,"dataId":0,"value":0.3},{"code":22,"dataId":2,"value":0.3},{"code":51,"dataId":2,"value":1},{"code":12,"dataId":0,"value":1.18}],"iconIndex":4786,"name":"Пламенный Меч","note":"50-60","params":[210,0,130,0,0,0,32,0],"price":0,"wtypeId":2},
{"id":73,"animationId":13,"description":"","etypeId":1,"traits":[{"code":31,"dataId":1,"value":0},{"code":22,"dataId":0,"value":0.33},{"code":22,"dataId":2,"value":0.33},{"code":22,"dataId":6,"value":0.15},{"code":51,"dataId":2,"value":1}],"iconIndex":6085,"name":"Меч Генерала","note":"60-70","params":[245,0,155,0,0,0,40,0],"price":0,"wtypeId":2},
{"id":74,"animationId":13,"description":"","etypeId":1,"traits":[{"code":31,"dataId":1,"value":0},{"code":22,"dataId":0,"value":0.37},{"code":22,"dataId":2,"value":0.36},{"code":12,"dataId":3,"value":1.25},{"code":12,"dataId":0,"value":1.17}],"iconIndex":4792,"name":"Драконий Меч","note":"70-80","params":[310,0,177,0,0,0,52,0],"price":0,"wtypeId":2},
{"id":75,"animationId":13,"description":"","etypeId":1,"traits":[{"code":31,"dataId":1,"value":0},{"code":22,"dataId":0,"value":0.4},{"code":22,"dataId":2,"value":0.4},{"code":12,"dataId":0,"value":1.3},{"code":12,"dataId":2,"value":1.3},{"code":12,"dataId":3,"value":1.3},{"code":51,"dataId":2,"value":1}],"iconIndex":5039,"name":"Экскалибур","note":"80-90","params":[400,0,200,0,0,0,67,0],"price":0,"wtypeId":2},
{"id":76,"animationId":10,"description":"","etypeId":1,"traits":[{"code":31,"dataId":1,"value":0},{"code":22,"dataId":0,"value":0.1},{"code":22,"dataId":2,"value":0.1},{"code":51,"dataId":1,"value":1}],"iconIndex":4336,"name":"Древний кинжал убийцы","note":"10-20","params":[0,0,30,0,0,0,15,0],"price":600,"wtypeId":1},
{"id":77,"animationId":10,"description":"","etypeId":1,"traits":[{"code":31,"dataId":1,"value":0},{"code":22,"dataId":0,"value":0.13},{"code":22,"dataId":2,"value":0.13},{"code":51,"dataId":1,"value":1}],"iconIndex":4713,"name":"Кинжал одиночки","note":"20-30","params":[0,0,40,0,0,0,19,0],"price":0,"wtypeId":1},
{"id":78,"animationId":10,"description":"","etypeId":1,"traits":[{"code":31,"dataId":1,"value":0},{"code":22,"dataId":0,"value":0.17},{"code":22,"dataId":2,"value":0.18},{"code":22,"dataId":1,"value":0.15},{"code":51,"dataId":1,"value":1},{"code":34,"dataId":0,"value":1}],"iconIndex":4338,"name":"Кинжал ветра","note":"30-40","params":[0,0,47,0,0,0,13,0],"price":0,"wtypeId":1},
{"id":79,"animationId":10,"description":"","etypeId":1,"traits":[{"code":31,"dataId":1,"value":0},{"code":22,"dataId":0,"value":0.24},{"code":22,"dataId":2,"value":0.2},{"code":22,"dataId":1,"value":0.2},{"code":51,"dataId":1,"value":1},{"code":34,"dataId":0,"value":1}],"iconIndex":5159,"name":"Семь далеких звезд","note":"40-50","params":[0,0,56,0,0,0,19,0],"price":0,"wtypeId":1},
{"id":80,"animationId":10,"description":"","etypeId":1,"traits":[{"code":31,"dataId":1,"value":0},{"code":22,"dataId":0,"value":0.26},{"code":22,"dataId":2,"value":0.24},{"code":22,"dataId":1,"value":0.25},{"code":51,"dataId":1,"value":1},{"code":34,"dataId":0,"value":1}],"iconIndex":5162,"name":"Шипы заоблачных миров","note":"50-60","params":[0,0,70,0,0,0,27,0],"price":0,"wtypeId":1},
{"id":81,"animationId":10,"description":"","etypeId":1,"traits":[{"code":31,"dataId":1,"value":0},{"code":22,"dataId":0,"value":0.3},{"code":22,"dataId":2,"value":0.32},{"code":51,"dataId":1,"value":1},{"code":22,"dataId":1,"value":0.28},{"code":34,"dataId":0,"value":1}],"iconIndex":5194,"name":"Лунный кинжал","note":"60-70","params":[0,0,82,0,0,0,33,0],"price":0,"wtypeId":1},
{"id":82,"animationId":10,"description":"","etypeId":1,"traits":[{"code":31,"dataId":1,"value":0},{"code":22,"dataId":0,"value":0.35},{"code":22,"dataId":2,"value":0.32},{"code":51,"dataId":1,"value":1},{"code":34,"dataId":0,"value":1},{"code":22,"dataId":1,"value":0.3},{"code":12,"dataId":3,"value":1.15}],"iconIndex":4764,"name":"Кинжал хаоса","note":"70-80","params":[0,0,93,0,0,0,40,0],"price":0,"wtypeId":1},
{"id":83,"animationId":10,"description":"","etypeId":1,"traits":[{"code":31,"dataId":1,"value":0},{"code":22,"dataId":0,"value":0.4},{"code":22,"dataId":2,"value":0.37},{"code":22,"dataId":1,"value":0.35},{"code":51,"dataId":1,"value":1},{"code":34,"dataId":0,"value":1},{"code":12,"dataId":0,"value":1.25}],"iconIndex":5327,"name":"Смех из загробного мира","note":"80-90","params":[0,0,105,0,0,0,55,0],"price":0,"wtypeId":1},
{"id":84,"animationId":11,"description":"","etypeId":1,"traits":[{"code":31,"dataId":1,"value":0},{"code":22,"dataId":0,"value":0.12},{"code":22,"dataId":2,"value":0.1},{"code":51,"dataId":7,"value":1}],"iconIndex":4368,"name":"Бамбуковый лук","note":"10-20","params":[0,0,23,0,0,0,10,0],"price":0,"wtypeId":7},
{"id":85,"animationId":11,"description":"","etypeId":1,"traits":[{"code":31,"dataId":1,"value":0},{"code":22,"dataId":0,"value":0.18},{"code":22,"dataId":2,"value":0.15},{"code":51,"dataId":7,"value":1}],"iconIndex":5669,"name":"Лук меткости","note":"20-30","params":[0,0,35,0,0,0,17,0],"price":0,"wtypeId":7},
{"id":86,"animationId":11,"description":"","etypeId":1,"traits":[{"code":31,"dataId":1,"value":0},{"code":22,"dataId":2,"value":0.22},{"code":22,"dataId":0,"value":0.25},{"code":51,"dataId":7,"value":1},{"code":12,"dataId":0,"value":1.15}],"iconIndex":5649,"name":"Лук феникса","note":"30-40","params":[0,0,52,0,0,0,25,0],"price":0,"wtypeId":7},
{"id":87,"animationId":11,"description":"","etypeId":1,"traits":[{"code":31,"dataId":1,"value":0},{"code":22,"dataId":0,"value":0.29},{"code":22,"dataId":2,"value":0.26},{"code":51,"dataId":7,"value":1},{"code":12,"dataId":3,"value":1.13}],"iconIndex":4377,"name":"Орлиный глаз","note":"40-50","params":[0,0,68,0,0,0,33,0],"price":0,"wtypeId":7},
{"id":88,"animationId":11,"description":"","etypeId":1,"traits":[{"code":31,"dataId":1,"value":0},{"code":22,"dataId":0,"value":0.34},{"code":22,"dataId":2,"value":0.34},{"code":51,"dataId":7,"value":1},{"code":12,"dataId":3,"value":1.1},{"code":12,"dataId":0,"value":1.1},{"code":12,"dataId":2,"value":1.1}],"iconIndex":4399,"name":"Лук небесной армии","note":"50-60","params":[0,0,84,0,0,0,42,0],"price":0,"wtypeId":7},
{"id":89,"animationId":11,"description":"","etypeId":1,"traits":[{"code":31,"dataId":1,"value":0},{"code":22,"dataId":0,"value":0.39},{"code":22,"dataId":2,"value":0.37},{"code":51,"dataId":7,"value":1},{"code":12,"dataId":0,"value":1.2}],"iconIndex":5715,"name":"Лук небесного стрелка","note":"60-70","params":[0,0,99,0,0,0,49,0],"price":0,"wtypeId":7},
{"id":90,"animationId":11,"description":"","etypeId":1,"traits":[{"code":31,"dataId":1,"value":0},{"code":22,"dataId":0,"value":0.43},{"code":22,"dataId":2,"value":0.41},{"code":51,"dataId":7,"value":1},{"code":12,"dataId":3,"value":1.17},{"code":12,"dataId":2,"value":1.08}],"iconIndex":5914,"name":"Длинный лук охотника-тени","note":"70-80","params":[0,0,123,0,0,0,54,0],"price":0,"wtypeId":7},
{"id":91,"animationId":11,"description":"","etypeId":1,"traits":[{"code":31,"dataId":1,"value":0},{"code":22,"dataId":0,"value":0.45},{"code":22,"dataId":2,"value":0.45},{"code":12,"dataId":3,"value":1.25},{"code":13,"dataId":1,"value":1.15},{"code":12,"dataId":0,"value":1.25}],"iconIndex":5647,"name":"Большой лук бога луны","note":"80-90","params":[0,0,160,0,0,0,65,0],"price":0,"wtypeId":7},
{"id":92,"animationId":12,"description":"","etypeId":1,"traits":[{"code":31,"dataId":1,"value":0},{"code":51,"dataId":6,"value":1},{"code":21,"dataId":4,"value":1.05},{"code":22,"dataId":8,"value":0.05}],"iconIndex":4644,"name":"Посох из оленьего рога","note":"10-20","params":[0,30,0,0,15,0,0,10],"price":0,"wtypeId":6},
{"id":93,"animationId":12,"description":"","etypeId":1,"traits":[{"code":31,"dataId":1,"value":0},{"code":51,"dataId":6,"value":1},{"code":13,"dataId":1,"value":1.1},{"code":13,"dataId":4,"value":1.05}],"iconIndex":5303,"name":"Посох заклинателя","note":"20-30","params":[0,45,0,0,25,0,0,15],"price":0,"wtypeId":6},
{"id":94,"animationId":12,"description":"","etypeId":1,"traits":[{"code":31,"dataId":1,"value":0},{"code":12,"dataId":2,"value":1.1},{"code":12,"dataId":3,"value":1.1},{"code":13,"dataId":10,"value":1.1},{"code":51,"dataId":6,"value":1}],"iconIndex":5621,"name":"Посох призыва духов","note":"30-40","params":[0,70,0,0,47,0,0,22],"price":0,"wtypeId":6},
{"id":95,"animationId":12,"description":"","etypeId":1,"traits":[{"code":31,"dataId":1,"value":0},{"code":21,"dataId":4,"value":1.15},{"code":22,"dataId":7,"value":0.1},{"code":22,"dataId":2,"value":0.12},{"code":51,"dataId":6,"value":1},{"code":12,"dataId":5,"value":1.18}],"iconIndex":5615,"name":"Посох безумного демона","note":"40-50","params":[0,110,0,0,62,0,0,29],"price":0,"wtypeId":6},
{"id":96,"animationId":12,"description":"","etypeId":1,"traits":[{"code":22,"dataId":7,"value":0.15},{"code":12,"dataId":3,"value":1.18},{"code":12,"dataId":2,"value":1.16},{"code":51,"dataId":6,"value":1},{"code":31,"dataId":8,"value":1}],"iconIndex":5583,"name":"Посох солнечного света","note":"50-60","params":[0,145,0,0,78,0,0,36],"price":0,"wtypeId":6},
{"id":97,"animationId":12,"description":"","etypeId":1,"traits":[{"code":31,"dataId":1,"value":0},{"code":22,"dataId":8,"value":0.2},{"code":13,"dataId":8,"value":1.2},{"code":12,"dataId":0,"value":1.2},{"code":22,"dataId":8,"value":0.23},{"code":51,"dataId":6,"value":1}],"iconIndex":4646,"name":"Посох богов","note":"60-70","params":[0,175,3,0,90,0,0,42],"price":0,"wtypeId":6},
{"id":98,"animationId":12,"description":"","etypeId":1,"traits":[{"code":31,"dataId":4,"value":1},{"code":51,"dataId":6,"value":1},{"code":13,"dataId":1,"value":1.22},{"code":12,"dataId":3,"value":1.25},{"code":12,"dataId":0,"value":1.25},{"code":21,"dataId":4,"value":1.15}],"iconIndex":5312,"name":"Посох сотни молний","note":"70-80","params":[0,210,0,0,105,0,0,50],"price":0,"wtypeId":6},
{"id":99,"animationId":12,"description":"","etypeId":1,"traits":[{"code":22,"dataId":2,"value":0.2},{"code":12,"dataId":2,"value":1.23},{"code":12,"dataId":5,"value":1.25},{"code":13,"dataId":6,"value":1.15},{"code":21,"dataId":4,"value":1.3},{"code":31,"dataId":7,"value":1},{"code":51,"dataId":6,"value":1},{"code":22,"dataId":8,"value":0.25}],"iconIndex":5626,"name":"Посох небесного пути","note":"80-90","params":[0,300,0,0,135,0,0,63],"price":0,"wtypeId":6},
{"id":100,"animationId":14,"description":"","etypeId":1,"traits":[{"code":31,"dataId":1,"value":0},{"code":51,"dataId":4,"value":1},{"code":22,"dataId":7,"value":0.1},{"code":22,"dataId":0,"value":0.1}],"iconIndex":5394,"name":"Острая длинная секира","note":"10-20","params":[40,0,20,10,0,0,0,0],"price":0,"wtypeId":4},
{"id":101,"animationId":14,"description":"","etypeId":1,"traits":[{"code":31,"dataId":1,"value":0},{"code":22,"dataId":0,"value":0.13},{"code":51,"dataId":4,"value":1},{"code":21,"dataId":0,"value":1.1},{"code":21,"dataId":3,"value":1.1}],"iconIndex":5375,"name":"Секира доблести","note":"20-30","params":[75,0,26,18,0,0,0,0],"price":0,"wtypeId":4},
{"id":102,"animationId":14,"description":"","etypeId":1,"traits":[{"code":31,"dataId":1,"value":0},{"code":22,"dataId":0,"value":0.17},{"code":21,"dataId":0,"value":1.13},{"code":21,"dataId":3,"value":1.13},{"code":51,"dataId":4,"value":1}],"iconIndex":5354,"name":"Крушитель скал","note":"30-40","params":[110,0,33,30,0,0,0,0],"price":0,"wtypeId":4},
{"id":103,"animationId":14,"description":"","etypeId":1,"traits":[{"code":31,"dataId":1,"value":0},{"code":22,"dataId":0,"value":0.2},{"code":21,"dataId":0,"value":1.2},{"code":21,"dataId":3,"value":1.2},{"code":51,"dataId":4,"value":1}],"iconIndex":5432,"name":"Шестигранный молот","note":"40-50","params":[135,0,40,43,0,0,0,0],"price":0,"wtypeId":4},
{"id":104,"animationId":14,"description":"","etypeId":1,"traits":[{"code":31,"dataId":1,"value":0},{"code":22,"dataId":0,"value":0.23},{"code":21,"dataId":0,"value":1.25},{"code":21,"dataId":3,"value":1.25},{"code":51,"dataId":4,"value":1},{"code":22,"dataId":6,"value":0.2}],"iconIndex":5379,"name":"Сокрушающий небо топор","note":"50-60","params":[170,0,52,55,0,0,0,0],"price":0,"wtypeId":4},
{"id":105,"animationId":14,"description":"","etypeId":1,"traits":[{"code":31,"dataId":1,"value":0},{"code":22,"dataId":0,"value":0.28},{"code":21,"dataId":0,"value":1.3},{"code":21,"dataId":3,"value":1.3},{"code":51,"dataId":4,"value":1},{"code":22,"dataId":6,"value":0.25},{"code":22,"dataId":1,"value":0.2}],"iconIndex":5358,"name":"Грозовое небо","note":"60-70","params":[135,0,64,75,0,0,0,0],"price":0,"wtypeId":4},
{"id":106,"animationId":14,"description":"","etypeId":1,"traits":[{"code":31,"dataId":1,"value":0},{"code":22,"dataId":0,"value":0.33},{"code":21,"dataId":0,"value":1.36},{"code":21,"dataId":3,"value":1.36},{"code":51,"dataId":4,"value":1},{"code":22,"dataId":6,"value":0.3},{"code":22,"dataId":1,"value":0.25}],"iconIndex":5441,"name":"Секира бессмертного короля","note":"70-80","params":[195,0,75,110,0,0,0,0],"price":0,"wtypeId":4},
{"id":107,"animationId":14,"description":"","etypeId":1,"traits":[{"code":31,"dataId":1,"value":0},{"code":22,"dataId":0,"value":0.37},{"code":21,"dataId":0,"value":1.45},{"code":21,"dataId":3,"value":1.4},{"code":21,"dataId":2,"value":1.3},{"code":51,"dataId":4,"value":1},{"code":22,"dataId":1,"value":0.28},{"code":22,"dataId":6,"value":0.35}],"iconIndex":5880,"name":"Божественная гармония","note":"80-90","params":[290,0,88,145,0,0,0,0],"price":0,"wtypeId":4},
{"id":108,"animationId":0,"description":"Бесполезная вешь.","etypeId":1,"traits":[{"code":31,"dataId":1,"value":0},{"code":22,"dataId":0,"value":0}],"iconIndex":331,"name":"Деревянные когти","note":"","params":[0,0,5,0,0,0,0,0],"price":5,"wtypeId":10},
{"id":109,"animationId":0,"description":"","etypeId":1,"traits":[{"code":31,"dataId":1,"value":0},{"code":22,"dataId":0,"value":0.1},{"code":22,"dataId":2,"value":0.1}],"iconIndex":4914,"name":"Бойцовские перчатки","note":"","params":[0,0,10,0,0,0,5,0],"price":100,"wtypeId":11},
{"id":110,"animationId":0,"description":"","etypeId":1,"traits":[{"code":31,"dataId":1,"value":0},{"code":22,"dataId":0,"value":0}],"iconIndex":0,"name":"","note":"","params":[0,0,0,0,0,0,0,0],"price":0,"wtypeId":0},
{"id":111,"animationId":0,"description":"","etypeId":1,"traits":[{"code":31,"dataId":1,"value":0},{"code":22,"dataId":0,"value":0}],"iconIndex":0,"name":"","note":"","params":[0,0,0,0,0,0,0,0],"price":0,"wtypeId":0}
]